{
  "code": "0",
  "msg": "",
  "data": [
    {
      "projectName": "上海",
      "buildTime": "2016/02/15",
      "buildingType": "商品住宅",
      "buildingType2": "联体别墅",
      "buildingScale": "222",
      "provider": "木子李",
      "provideTime": "2016/02/15"
    },{
      "projectName": "上海",
      "buildTime": "2016/02/15",
      "buildingType": "商品住宅",
      "buildingType2": "联体别墅",
      "buildingScale": "222",
      "provider": "木子李",
      "provideTime": "2016/02/15"
    },{
      "projectName": "上海",
      "buildTime": "2016/02/15",
      "buildingType": "商品住宅",
      "buildingType2": "联体别墅",
      "buildingScale": "222",
      "provider": "木子李",
      "provideTime": "2016/02/15"
    },{
      "projectName": "上海",
      "buildTime": "2016/02/15",
      "buildingType": "商品住宅",
      "buildingType2": "联体别墅",
      "buildingScale": "222",
      "provider": "木子李",
      "provideTime": "2016/02/15"
    },{
      "projectName": "上海",
      "buildTime": "2016/02/15",
      "buildingType": "商品住宅",
      "buildingType2": "联体别墅",
      "buildingScale": "222",
      "provider": "木子李",
      "provideTime": "2016/02/15"
    },{
      "projectName": "上海",
      "buildTime": "2016/02/15",
      "buildingType": "商品住宅",
      "buildingType2": "联体别墅",
      "buildingScale": "222",
      "provider": "木子李",
      "provideTime": "2016/02/15"
    },{
      "projectName": "上海",
      "buildTime": "2016/02/15",
      "buildingType": "商品住宅",
      "buildingType2": "联体别墅",
      "buildingScale": "222",
      "provider": "木子李",
      "provideTime": "2016/02/15"
    }
  ]
}